Workbook
Name EDILE_NOMI: #REF!
Name EDILE_PERC: #REF!
Name PROG_NOMI: #REF!
Name PROG_PERC: #REF!
Name SICUREZZA_NOMI: #REF!
Name SICUREZZA_PERC: #REF!

Sheet Analisi preliminareTOTALI
A1: Riepilogo
F3: Data : 29/05/2025
A6: Dati Cliente
A8: Cliente caso 04
A9: Indirizzo
A10: Reggio Emilia (RE)
A17: RIEPILOGO TOTALI | H17: Celle correttive
B20: A-EDILE iva inclusa 10% | F20: ='A-EDILE'!G196 -> 92224
B22: B-FINITURE iva inclusa 22% | F22: ='B-FINITURE'!E82 -> 0
B24: C-PORTE E SERRAMENTI iva inclusa 10% | F24: ='C- SERRAMENTI PORTE '!E34 -> 0
B26: D-PRODOTTI iva inclusa 10% | F26: ='D- PRODOTTI'!E29 -> 0
F28: =(F22+F24+F26)*0.07 -> 0
A30: TOTALE iva inclusa | F30: =F20+F22+F24+F26+F28 -> 92224
B34: NOMINA DI CSE/CSP inclusa iva e contrubuti
B35: PRATICHE AMMINISTRATIVE inclusa iva e contrubuti
A36: TOTALE | F36: =F34++F35 -> 0
A38: da pagare iva INCLUSA | F38: =F36+F30 -> 92224
A43: FINANZIAMENTO
A44: PER TOTALE LAVORI TRA 25 E 50K | D44: n.RATE | E44: rata/mese
D45: 48 | E45: =F30/D45/2 -> 960.66667
A46: PER TOTALE LAVORI TRA 50K E 100K
D47: 60 | E47: =F30/D47/2 -> 768.53333
A49: Si informa che la divisione dei costi sopra elencati verrà sottoposta ad approvazione da parte del partner finanziario fiditalia

Sheet A-EDILE
C1: Computo | Elenco Lavorazioni
G2: ='Analisi preliminareTOTALI'!F3 -> Data : 29/05/2025
B4: Le voci di seguito riportate ed utilizzate nel computo, sono state redatte per l'individuazioni dei lavori da effettuare secondo progetto approvato. Le misure sono calcolate da disegno, eventuali differenze sono da considerare tolleranze progettuali. Si richiede alle imprese di verificare le lavorazioni e segnalare eventuali dimenticanze/discrepanze e/o migliorie.
B6: Dati Cliente
B8: ='Analisi preliminareTOTALI'!A8 -> Cliente caso 04
B9: ='Analisi preliminareTOTALI'!A9 -> Indirizzo
B10: ='Analisi preliminareTOTALI'!A10 -> Reggio Emilia (RE)
B11: ='Analisi preliminareTOTALI'!A11 -> 0
B12: ='Analisi preliminareTOTALI'!A12 -> 0
B13: ='Analisi preliminareTOTALI'!A13 -> 0
B15: DESCRIZIONE SINTETICA DELLE OPERE DA ESEGUIRE COMPUTATE DI SEGUITO
B16: Appartamento posto al primo piano di fabbricato plurifamiliare. Ristrutturazione Totale
C25: DESCRIZIONE | D25: UM: | E25: Qta: | F25: Prezzo U. | G25: Totale | J25: Listino | K25: TOTALE IMPRESA | L25: TOTALE IMPRESA | N25: Fee arch. | O25: Guadagno | P25: Percentuale
B26: A | C26: ALLESTIMENTO DI CANTIERE | H26: NOTE(non stampare mai) | J26: 0.65 | K26: Prezzo Unità | L26: Totale | M26: Sal gg
A27: EDILE | B27: A.1 | C27: Allestimento area di cantiere con protezione zone di passaggio a mezzo teli nylon e/o cartoni al fine di eseguire i lavori in oggetto a perfetta regola d'arte, a norma ed in sicurezza. Fornitura ed installazione cartello di cantiere, DPI lavoratori e POS. | D27: ac | E27: 1 | F27: 1500 | G27: =F27*E27 -> 1500 | H27: L'allestimento di cantire deve essere sempre presente e dovrà essere calcolata nel seguente modo: per appartamenti fino a 100 mq - 600 | K27: =F27*$J$26 -> 975 | L27: =E27*K27 -> 975 | N27: =G27*0.05 -> 75 | O27: =G27-L27-N27 -> 450 | P27: =O27/G27 -> 0.3
A28: ELETTRICO | B28: A.2 | C28: Installazione di quadro elettrico di cantiere effettuato da operatore abilitato, e rilascio della certificazioni di installazione e conformità valido per tutta la durata del cantiere. | D28: ac | E28: 1 | F28: 150 | G28: =F28*E28 -> 150 | H28: Il quadro mobile per cantiere deve essere presente. | K28: =F28*$J$26 -> 97.5 | L28: =E28*K28 -> 97.5 | N28: =G28*0.05 -> 7.5 | O28: =G28-L28-N28 -> 45 | P28: =O28/G28 -> 0.3
A29: EDILE | B29: A.3 | C29: Rimozione di apparecchi idro-termo-sanitari, incluso lo smontaggio delle apparecchiature, rubinetterie e degli accessori e chiusura delle adduzioni con tappi. Compreso il carico da piano strada e trasporto ad impianti di stoccaggio, di recupero o a discarica | H29: Questa voce deve essere presente nel caso di rifacimento di uno o più bagni
A30: EDILE | C30: a piatto doccia | D30: cad | E30: 2 | F30: 40 | G30: =F30*E30 -> 80 | K30: =F30*$J$26 -> 26 | L30: =E30*K30 -> 52 | N30: =G30*0.05 -> 4 | O30: =G30-L30-N30 -> 24 | P30: =O30/G30 -> 0.3
A31: EDILE | C31: b vasca da bagno | D31: cad | E31: 2 | F31: 40 | G31: =F31*E31 -> 80 | K31: =F31*$J$26 -> 26 | L31: =E31*K31 -> 52 | N31: =G31*0.05 -> 4 | O31: =G31-L31-N31 -> 24 | P31: =O31/G31 -> 0.3
A32: EDILE | C32: c vaso igienico (WC) | D32: cad | E32: 2 | F32: 40 | G32: =F32*E32 -> 80 | K32: =F32*$J$26 -> 26 | L32: =E32*K32 -> 52 | N32: =G32*0.05 -> 4 | O32: =G32-L32-N32 -> 24 | P32: =O32/G32 -> 0.3
A33: EDILE | C33: d bidet | D33: cad | E33: 2 | F33: 40 | G33: =F33*E33 -> 80 | K33: =F33*$J$26 -> 26 | L33: =E33*K33 -> 52 | N33: =G33*0.05 -> 4 | O33: =G33-L33-N33 -> 24 | P33: =O33/G33 -> 0.3
A34: EDILE | C34: e lavabo singolo su mensola | D34: cad | E34: 0 | F34: 40 | G34: =F34*E34 -> 0 | K34: =F34*$J$26 -> 26 | L34: =E34*K34 -> 0 | N34: =G34*0.05 -> 0 | O34: =G34-L34-N34 -> 0 | P34: =O34/G34 -> #DIV/0!
A35: EDILE | C35: f lavello da cucina in porcellana | D35: cad | E35: 0 | F35: 40 | G35: =F35*E35 -> 0 | K35: =F35*$J$26 -> 26 | L35: =E35*K35 -> 0 | N35: =G35*0.05 -> 0 | O35: =G35-L35-N35 -> 0 | P35: =O35/G35 -> #DIV/0!
A36: EDILE | C36: g scaldabagno elettrico | D36: cad | E36: 0 | F36: 40 | G36: =F36*E36 -> 0 | K36: =F36*$J$26 -> 26 | L36: =E36*K36 -> 0 | N36: =G36*0.05 -> 0 | O36: =G36-L36-N36 -> 0 | P36: =O36/G36 -> #DIV/0!
A37: EDILE | C37: h cassetta alta di scarico | D37: cad | E37: 0 | F37: 40 | G37: =F37*E37 -> 0 | K37: =F37*$J$26 -> 26 | L37: =E37*K37 -> 0 | N37: =G37*0.05 -> 0 | O37: =G37-L37-N37 -> 0 | P37: =O37/G37 -> #DIV/0!
A38: IDRAULICO | B38: A.4 | C38: Rimozione delle linee di alimentazione degli apparecchi igienicosanitari (linea acqua calda e linea acqua fredda) fino alle valvole di intercettazione e delle relative tubazioni di scarico fino alla colonna principale. Compresi i tagli, le intercettazioni, le opere provvisionali di sostegno e protezione. Compreso il carico da piano strada e trasporto ad impianti di stoccaggio, di recupero o a discarica. | D38: ac | E38: 1 | F38: 300 | G38: =F38*E38 -> 300 | H38: Questa voce deve essere presente nel caso di rifacimento di uno o più bagni. Dovrà essere computata una linea da rimuovere per ogni bagno da rifare. | K38: =F38*$J$26 -> 195 | L38: =E38*K38 -> 195 | N38: =G38*0.05 -> 15 | O38: =G38-L38-N38 -> 90 | P38: =O38/G38 -> 0.3
A39: EDILE | B39: A.5 | C39: Rimozione di tutte le porte interne comprese di anta, telaio e falso telaio con trasposto dal piano strada alle pubbliche discariche. Compreso il carico da piano strada e trasporto ad impianti di stoccaggio, di recupero o a discarica. | D39: cad | E39: 14 | F39: 50 | G39: =F39*E39 -> 700 | K39: =F39*$J$26 -> 32.5 | L39: =E39*K39 -> 455 | N39: =G39*0.05 -> 35 | O39: =G39-L39-N39 -> 210 | P39: =O39/G39 -> 0.3
A40: EDILE | B40: A.6 | C40: Rimozione dei corpi riscaldanti in alluminio e/o ghisa presenti all'interno dell'immobile.Compreso il carico da piano strada e trasporto ad impianti di stoccaggio, di recupero o a discarica.
A41: EDILE | C41: radiatori in ghisa e/o in alluminio:
A42: EDILE | C42: a fino a 15 elementi, per radiatore | D42: cad | E42: 8 | F42: 80 | G42: =F42*E42 -> 640 | K42: =F42*$J$26 -> 52 | L42: =E42*K42 -> 416 | N42: =G42*0.05 -> 32 | O42: =G42-L42-N42 -> 192 | P42: =O42/G42 -> 0.3
A43: EDILE | C43: b da 7 a 12 elementi, per radiatore | D43: cad | E43: 0 | F43: 51 | G43: =F43*E43 -> 0 | K43: =F43*$J$26 -> 33.15 | L43: =E43*K43 -> 0 | N43: =G43*0.05 -> 0 | O43: =G43-L43-N43 -> 0 | P43: =O43/G43 -> #DIV/0!
A44: EDILE | C44: c da 13 a 20 elementi, per radiatore | D44: cad | E44: 0 | F44: 51 | G44: =F44*E44 -> 0 | K44: =F44*$J$26 -> 33.15 | L44: =E44*K44 -> 0 | N44: =G44*0.05 -> 0 | O44: =G44-L44-N44 -> 0 | P44: =O44/G44 -> #DIV/0!
A45: IDRAULICO | B45: A.7 | C45: Rimozione di condizionatore autonomo monosplit costituito da motocondensante esterna e macchina interna, compreso l'onere del recupero gas e l'avvicinamento al luogo di deposito provvisorio in attesa di trasporto a discarica, esclusa la rimozione delle tubazioni di collegamento ed i cavi di alimentazione elettrica:
A46: IDRAULICO | C46: a macchina interna a parete alta o soffitto | D46: cad | E46: 0 | F46: 80 | G46: =F46*E46 -> 0 | K46: =F46*$J$26 -> 52 | L46: =E46*K46 -> 0 | N46: =G46*0.05 -> 0 | O46: =G46-L46-N46 -> 0 | P46: =O46/G46 -> #DIV/0!
A47: IDRAULICO | C47: b macchina interna a parete bassa o pavimento. | D47: cad | E47: 0 | F47: 80 | G47: =F47*E47 -> 0 | K47: =F47*$J$26 -> 52 | L47: =E47*K47 -> 0 | N47: =G47*0.05 -> 0 | O47: =G47-L47-N47 -> 0 | P47: =O47/G47 -> #DIV/0!
A48: EDILE | B48: A.8 | C48: Movimentazione nell'area di cantiere di materiali di risulta e assistenza con personale per il carico di tutte le forniture (quali ad esempio pavimenti, rivestimenti, sanitari, ecc.) esclusi gli infissi. Compresa l'immediata verifica degli stessi in riferimento alla corrispondenza di quantità e qualità riportate sui vari documenti di trasporto) per tutto il periodo di durata dei lavori. Si ritiene da verificare la possibilità di installare un argano e di parcheggiare il mezzo di trasporto ai piedi dell'argano. | D48: piano | E48: 1 | F48: 2000 | G48: =F48*E48 -> 2000 | H48: Questa voce deve essere presente. Il tecnico dovrà riportare nella formula il numero del piano (ad esempio: *1 se è piano primo, *2 se è piano secondo ecc). Si precisa che normalmente la consegna delle forniture è effettuata all’indirizzo indicato dal Cliente al termine del processo di acquisto, con scarico al piano terra del numero civico. Questa voce, pertanto, include: 1) la consegna delle forniture all’interno dell’abitazione del Cliente; 2) il controllo, al momento della consegna, del numero dei colli in consegna e dell'integrità dell’imballo; 3) movimentazione del materiale di risulta. | K48: =F48*$J$26 -> 1300 | L48: =E48*K48 -> 1300 | N48: =G48*0.05 -> 100 | O48: =G48-L48-N48 -> 600 | P48: =O48/G48 -> 0.3 | T48: CIRCA 2000-2500 APPP 100 MQ PIANO
B49: A | C49: TOTALE ALLESTIMENTO DI CANTIERE | G49: =SUM(G27:G48) -> 5610 | L49: =SUM(L27:L48) -> 3646.5 | N49: =SUM(N27:N48) -> 280.5 | O49: =SUM(O27:O48) -> 1683 | P49: =O49/F49 -> #DIV/0!
B51: A.1 | C51: DEMOLIZIONI - RIMOZIONI - TRASPORTO
A52: EDILE | B52: A.1.1 | C52: Demolizione di muratura di tamponamento e di tramezzi spessore da 8 a 12 cm, compresi intonaci, eseguita anche con l'ausilio di idonei mezzi. Compreso l’accatastamento nei siti che verranno indicati dalla Direzione dei lavori nell'ambito del cantiere. Compreso il carico da piano strada e trasporto ad impianti di stoccaggio, di recupero o a discarica. SECONDO PROGETTO
A53: EDILE | C53: a muratura in mattoni pieni | D53: mq | E53: 0 | F53: 42.5 | G53: =F53*E53 -> 0 | K53: =F53*$J$26 -> 27.625 | L53: =E53*K53 -> 0 | N53: =G53*0.05 -> 0 | O53: =G53-L53-N53 -> 0 | P53: =O53/G53 -> #DIV/0!
A54: EDILE | C54: b muratura in mattoni forati | D54: mq | E54: 30 | F54: 30 | G54: =F54*E54 -> 900 | K54: =F54*$J$26 -> 19.5 | L54: =E54*K54 -> 585 | N54: =G54*0.05 -> 45 | O54: =G54-L54-N54 -> 270 | P54: =O54/F54 -> 9
A55: EDILE | B55: A.1.2 | C55: Demolizione di muratura di tamponamento di tramezzi in cartongesso spessore fino a 12,5 cm, eseguita anche con l'ausilio di idonei mezzi. Compreso l’accatastamento nei siti idonei. Compreso il carico da piano strada e trasporto ad impianti di stoccaggio, di recupero o a discarica come rifiuto speciale. | D55: mq | E55: 0 | F55: 40 | G55: =F55*E55 -> 0 | K55: =F55*$J$26 -> 26 | L55: =E55*K55 -> 0 | N55: =G55*0.05 -> 0 | O55: =G55-L55-N55 -> 0 | P55: =O55/F55 -> 0
A56: EDILE | B56: A.1.3 | C56: Demolizione di controsoffitti in cartongesso eseguita anche con l'ausilio di idonei mezzi. Compreso l’accatastamento nei siti che verranno indicati dalla Direzione dei lavori nell'ambito del cantiere. Compreso il carico da piano strada e trasporto ad impianti di stoccaggio, di recupero o a discarica come rifiuto speciale. | D56: mq | E56: 0 | F56: 40 | G56: =F56*E56 -> 0 | K56: =F56*$J$26 -> 26 | L56: =E56*K56 -> 0 | N56: =G56*0.05 -> 0 | O56: =G56-L56-N56 -> 0 | P56: =O56/F56 -> 0
A57: EDILE | B57: A.1.4 | C57: Spicconatura di intonaco a vivo di muro, di spessore fino a 3 cm compresi l’onere di esecuzione anche a piccole zone, la spazzolatura delle superfici, l’accatastamento nell'ambito del cantiere, incluso il trasporto a rifiuto in discarica autorizzata del materiale inutilizzabile. | D57: mq | E57: 0 | F57: 19 | G57: =F57*E57 -> 0 | H57: Questa voce deve essere presente nel caso di rimozione di intonaco ammalorato. L'asportazione di intonaco, mediante demolizione con attrezzature meccaniche e/o con attrezzi manuali, viene eseguita solitamente su intonaci ammalorati fino al vivo della muratura sottostante, per valutarne lo stato di conservazione e degrado ed effettuare le necessarie operazioni di ripristino. | K57: =F57*$J$26 -> 12.35 | L57: =E57*K57 -> 0 | N57: =G57*0.05 -> 0 | O57: =G57-L57-N57 -> 0 | P57: =O57/F57 -> 0
A58: EDILE | B58: A.1.5 | C58: Demolizione di pavimento e battiscopa, compreso il sottofondo dello spessore fino a 8 cm, posto in opera a mezzo di malta o colla. Compreso l’accatastamento nei siti che verranno indicati dalla Direzione dei lavori nell'ambito del cantiere. Compreso il carico da piano strada e trasporto ad impianti di stoccaggio, di recupero o a discarica. INTERNO + TERRAZZA | D58: mq | E58: =125+70 -> 195 | F58: 30 | G58: =F58*E58 -> 5850 | H58: Questa voce deve essere presente nel caso di rifacimento di bagni, posa di nuovo impianto di riscaldamento tradizionale e/o riscaldamento a pavimento. Si dovrà prevedere il successivo rifacimento del massetto e posa pavimentazione. Si precisa che la stratigrafia vede solaio, su cui vengono appoggiati e fissati gli impianti, quindi strato di sottofondo, che ingloba le tubazioni ed infine il massetto, sul quale sarà incollata la pavimentazione. | K58: =F58*$J$26 -> 19.5 | L58: =E58*K58 -> 3802.5 | N58: =G58*0.05 -> 292.5 | O58: =G58-L58-N58 -> 1755 | P58: =O58/F58 -> 58.5
A59: EDILE | B59: A.1.6 | C59: Demolizione di pavimento e battiscopa (in gres o similari), escluso il sottofondo, posto in opera a mezzo di malta o colla, calo in basso e l’avvicinamento al luogo di deposito provvisorio nell’ambito del cantiere Compreso l’accatastamento nei siti che verranno indicati dalla Direzione dei lavori nell'ambito del cantiere. Compreso il carico da piano strada e trasporto ad impianti di stoccaggio, di recupero o a discarica.. | D59: mq | E59: 0 | F59: 18 | G59: =F59*E59 -> 0 | K59: =F59*$J$26 -> 11.7 | L59: =E59*K59 -> 0 | N59: =G59*0.05 -> 0 | O59: =G59-L59-N59 -> 0 | P59: =O59/F59 -> 0
A60: EDILE | B60: A.1.7 | C60: Demolizione di pavimento in parquet, escluso il sottofondo, posto in opera a mezzo di colla. Compreso l’accatastamento nei siti che verranno indicati dalla Direzione dei lavori nell'ambito del cantiere. Compreso il carico da piano strada e trasporto ad impianti di stoccaggio, di recupero o a discarica. | D60: mq | E60: 0 | F60: 20 | G60: =F60*E60 -> 0 | K60: =F60*$J$26 -> 13 | L60: =E60*K60 -> 0 | N60: =G60*0.05 -> 0 | O60: =G60-L60-N60 -> 0 | P60: =O60/F60 -> 0
A61: EDILE | B61: A.1.8 | C61: Demolizione di battiscopa in legno. Compreso l’accatastamento nei siti che verranno indicati dalla Direzione dei lavori nell'ambito del cantiere. Compreso il carico da piano strada e trasporto ad impianti di stoccaggio, di recupero o a discarica. | D61: ml | E61: 0 | F61: 6.5 | G61: =F61*E61 -> 0 | K61: =F61*$J$26 -> 4.225 | L61: =E61*K61 -> 0 | N61: =G61*0.05 -> 0 | O61: =G61-L61-N61 -> 0 | P61: =O61/F61 -> 0
A62: EDILE | B62: A.1.9 | C62: Demolizione di battiscopa in ceramica, con successivo ripristino delle parti di muratura interessate, pronto per pitturazione. Compreso l’accatastamento nei siti che verranno indicati dalla Direzione dei lavori nell'ambito del cantiere. Compreso il carico da piano strada e trasporto ad impianti di stoccaggio, di recupero o a discarica. | D62: ml | E62: 0 | F62: 15 | G62: =F62*E62 -> 0 | K62: =F62*$J$26 -> 9.75 | L62: =E62*K62 -> 0 | N62: =G62*0.05 -> 0 | O62: =G62-L62-N62 -> 0 | P62: =O62/F62 -> 0
A63: EDILE | B63: A.1.10 | C63: Demolizione di rivestimenti a parete, compresa la demolizione della sottostante malta di allettamento. Compreso l’accatastamento nei siti che verranno indicati dalla Direzione dei lavori nell'ambito del cantiere. Compreso il carico da piano strada e trasporto ad impianti di stoccaggio, di recupero o a discarica. BAGNI E CUCINA | D63: mq | E63: 26 | F63: 20 | G63: =F63*E63 -> 520 | K63: =F63*$J$26 -> 13 | L63: =E63*K63 -> 338 | N63: =G63*0.05 -> 26 | O63: =G63-L63-N63 -> 156 | P63: =O63/F63 -> 7.8
A64: EDILE | B64: A.1.11 | C64: Rimozione di carta da parati fino a due strati di carta.Compreso l’accatastamento nei siti che verranno indicati dalla Direzione dei lavori nell'ambito del cantiere. Compreso il carico da piano strada e trasporto ad impianti di stoccaggio, di recupero o a discarica. SECONDO PROGETTO | O64: =G64-L64-N64 -> 0
A65: EDILE | C65: a per uno strato. | D65: mq | E65: 60 | F65: 8 | G65: =F65*E65 -> 480 | K65: =F65*$J$26 -> 5.2 | L65: =E65*K65 -> 312 | N65: =G65*0.05 -> 24 | O65: =G65-L65-N65 -> 144 | P65: =O65/F65 -> 18
A66: EDILE | C66: b per ogni strato sottostante in più | D66: mq | E66: 0 | F66: 6 | G66: =F66*E66 -> 0 | K66: =F66*$J$26 -> 3.9 | L66: =E66*K66 -> 0 | N66: =G66*0.05 -> 0 | O66: =G66-L66-N66 -> 0 | P66: =O66/F66 -> 0
A67: EDILE | B67: A.1.12 | C67: Demolizione di guaina bituminosa (strato impermeabilizzante) Compreso l’accatastamento nei siti che verranno indicati dalla Direzione dei lavori nell'ambito del cantiere. Compreso il carico da piano strada e trasporto ad impianti di stoccaggio, di recupero o a discarica. | D67: mq | E67: 0 | F67: 20 | G67: =F67*E67 -> 0 | K67: =F67*$J$26 -> 13 | L67: =E67*K67 -> 0 | N67: =G67*0.05 -> 0 | O67: =G67-L67-N67 -> 0 | P67: =O67/F67 -> 0
A68: EDILE | B68: A.1.13 | C68: Rimozione gradini ad altezza fino a 15cm.Compreso l’accatastamento nei siti che verranno indicati dalla Direzione dei lavori nell'ambito del cantiere. Compreso il carico da piano strada e trasporto ad impianti di stoccaggio, di recupero o a discarica. | D68: ac | E68: 0 | F68: 650 | G68: =F68*E68 -> 0 | K68: =F68*$J$26 -> 422.5 | L68: =E68*K68 -> 0 | N68: =G68*0.05 -> 0 | O68: =G68-L68-N68 -> 0 | P68: =O68/F68 -> 0
A69: EDILE | B69: A.1.14 | C69: Apertura di Varco su muratura strutturale fino a 30 cm di profondità, compresi intonaci, rivestimenti, eseguita anche con l'ausilio di idonei mezzi, compreso il tiro in discesa dei materiali, il trasporto, la cernita e l’accatastamento nei siti che verranno indicati dalla Direzione dei lavori nell'ambito del cantiere dei materiali riutilizzabili. Incluso il trasporto a rifiuto in discarica autorizzata del materiale. Comprensivo di messa in sicurezza della parete ed esclusa la cerchiatura, putrelle sostegni ed altro materiale idoneo che andrà computato a seguito di calcolo strutturale. | D69: ac | E69: 0 | F69: 700 | G69: =F69*E69 -> 0 | K69: =F69*$J$26 -> 455 | L69: =E69*K69 -> 0 | N69: =G69*0.05 -> 0 | O69: =G69-L69-N69 -> 0 | P69: =O69/F69 -> 0
A70: EDILE | B70: A.1.15 | C70: Apertura di Varco su solaio in laterocemente per alloggiamento scala interna, compresa la demolizione di pavimentazioni e massetti, eseguita anche con l'ausilio di idonei mezzi, compreso il tiro in discesa dei materiali, il trasporto, la cernita e l’accatastamento nei siti che verranno indicati dalla Direzione dei lavori nell'ambito del cantiere dei materiali riutilizzabili. Incluso il trasporto a rifiuto in discarica autorizzata del materiale. Comprensivo di messa in sicurezza del solaio ed esclusa la cerchiatura, putrelle sostegni ed altro materiale idoneoche andrà computata a seguito di calcolo strutturale. | D70: ac | E70: 0 | F70: 700 | G70: =F70*E70 -> 0 | K70: =F70*$J$26 -> 455 | L70: =E70*K70 -> 0 | N70: =G70*0.05 -> 0 | O70: =G70-L70-N70 -> 0 | P70: =O70/F70 -> 0
A71: EDILE | B71: A.1.16 | C71: Demolizione di scala interna, comprese eventuali soglie e corrimano, eseguita anche con l'ausilio di idonei mezzi, compreso il tiro in discesa dei materiali, il trasporto, la cernita e l’accatastamento nei siti che verranno indicati dalla Direzione dei lavori nell'ambito del cantiere dei materiali riutilizzabili. Incluso il trasporto a rifiuto in discarica autorizzata del materiale. | D71: ac | E71: 0 | F71: 810 | G71: =F71*E71 -> 0 | K71: =F71*$J$26 -> 526.5 | L71: =E71*K71 -> 0 | N71: =G71*0.05 -> 0 | O71: =G71-L71-N71 -> 0 | P71: =O71/F71 -> 0
B72: A.1 | C72: TOTALE DEMOLIZIONI, RIMOZIONI E TRASPORTO | E72: m | G72: =SUM(G53:G71) -> 7750 | L72: =SUM(L52:L71) -> 5037.5 | M72: =#REF!*0.2 -> #REF! | N72: =SUM(N52:N71) -> 387.5 | O72: =SUM(O52:O71) -> 2325 | P72: =O72/G72 -> 0.3
B74: A.2 | C74: MASSETTI
A75: EDILE | B75: A.2.1 | C75: Relizzazione Massetto di sabbia e cemento nelle proporzioni di kg 350 di cemento 32.5 per mc di sabbia dato in opera ben costipato e livellato per uno spessore finito pari a circa 8 cm. INTERNO + TERRAZZA | D75: mq | E75: 195 | F75: 30 | G75: =F75*E75 -> 5850 | H75: SE NON SI RIFà TUTTO MASSETTO, A CORPO CIRCA 1800 | K75: =F75*$J$26 -> 19.5 | L75: =E75*K75 -> 3802.5 | N75: =G75*0.05 -> 292.5 | O75: =G75-L75-N75 -> 1755 | P75: =O75/G75 -> 0.3
A76: EDILE | B76: A.2.2 | C76: Realizzazione Massetto premiscelato pronto all’impiego, tipo "Topcem®" costituito da malta premiscelata per la realizzazione di sottofondi esterni ed interni ad asciugamento rapido e ritiro fortemente compensato, idonei alla posa di pavimentazioni in materiale ceramico, cotto e pietre naturali dopo 4 ore, di pavimenti vinilici, moquette, parquet dopo 48 ore, con resistenza caratteristica a compressione dopo 48 ore di 30 N/mmq ed una umidità residua non inferiore al 2,5%. | D76: mq | E76: 0 | F76: 55 | G76: =F76*E76 -> 0 | K76: =F76*$J$26 -> 35.75 | L76: =E76*K76 -> 0 | N76: =G76*0.05 -> 0 | O76: =G76-L76-N76 -> 0 | P76: =O76/G76 -> #DIV/0!
A77: EDILE | B77: A.2.3 | C77: Realizzazione Massetto termoacustico, tipo "LecaCem®" costituito da malta premiscelata per la realizzazione di sottofondi monostrato alleggeriti , a norma di legge termica e acustica (U≤0.8 W/m²K e L’n,w ≤ 63dB).. Per ogni ulteriori 2cm verrà calcolato un sovrapprezzo di 18€/mq | D77: mq | E77: 0 | F77: 65 | G77: =F77*E77 -> 0 | K77: =F77*$J$26 -> 42.25 | L77: =E77*K77 -> 0 | N77: =G77*0.05 -> 0 | O77: =G77-L77-N77 -> 0 | P77: =O77/G77 -> #DIV/0!
A78: EDILE | B78: A.2.4 | C78: Realizzazione di vespaio aerato per una altezza totale fino a 30 cm mediante fornitura e posa in opera di casseforme in plastica riciclata tipo "Iglù®" per la rapida formazione, a secco, di una piattaforma pedonabile autoportante sopra cui eseguire la gettata di calcestruzzo per il riempimento del cassero fino alla sua sommità (a raso) e di una soletta superiore di 5 cm armata con rete elettrosaldata, livellata e tirata a frattazzo su cui realizzare la posa del massetto. | D78: mq | E78: 0 | F78: 89 | G78: =F78*E78 -> 0 | K78: =F78*$J$26 -> 57.85 | L78: =E78*K78 -> 0 | N78: =G78*0.05 -> 0 | O78: =G78-L78-N78 -> 0 | P78: =O78/G78 -> #DIV/0!
A79: EDILE | B79: A.2.5 | C79: Fornitura e posa in opera di autolivellante (spessore fino a 3mm) al fine di rendere le superfici pronte alla posa della pavimentaizone. | D79: mq | E79: 0 | F79: 38 | G79: =F79*E79 -> 0 | H79: Questa voce deve essere presente ogni qualvolta si rimuove la sola pavimentazione, o si va in sovapposizione alla stessa. | K79: =F79*$J$26 -> 24.7 | L79: =E79*K79 -> 0 | N79: =G79*0.05 -> 0 | O79: =G79-L79-N79 -> 0 | P79: =O79/G79 -> #DIV/0!
B80: A.2 | C80: TOTALE MASSETTI | G80: =SUM(G75:G79) -> 5850 | L80: =SUM(L75:L79) -> 3802.5 | N80: =SUM(N75:N79) -> 292.5 | O80: =SUM(O75:O79) -> 1755 | P80: =O80/G80 -> 0.3
B82: A.3 | C82: OPERE MURARIE
A83: EDILE | B83: A.3.1 | C83: Realizzazione di muratura di mattoni forati, da 8/10 cm posti in foglio con malta, mediante fornitura trasposto e posa, compresi oneri e magisteri per l’esecuzione di ammorsature e quanto altro si renda necessario a realizzare l’opera a perfetta regola d’arte. SECONDO PROGETTO | D83: mq | E83: 25 | F83: 45 | G83: =F83*E83 -> 1125 | K83: =F83*$J$26 -> 29.25 | L83: =E83*K83 -> 731.25 | N83: =G83*0.05 -> 56.25 | O83: =G83-L83-N83 -> 337.5 | P83: =O83/G83 -> 0.3
A84: EDILE | B84: A.3.2 | C84: Realizzazione di nicchia porta oggetti nel tramezzo del bagno grande. | D84: ac | E84: 1 | F84: 200 | G84: =F84*E84 -> 200 | K84: =F84*$J$26 -> 130 | L84: =E84*K84 -> 130 | N84: =G84*0.05 -> 10 | O84: =G84-L84-N84 -> 60 | P84: =O84/G84 -> 0.3
A85: EDILE | B85: A.3.3 | C85: Chiusura di nicchie sotto le finestre, dove richiesto, comprensivo di fornitura e posa di isolamento lana di roccia. | D85: ac | E85: 9 | F85: 150 | G85: =F85*E85 -> 1350 | K85: =F85*$J$26 -> 97.5 | L85: =E85*K85 -> 877.5 | N85: =G85*0.05 -> 67.5 | O85: =G85-L85-N85 -> 405 | P85: =O85/G85 -> 0.3
A86: EDILE | B86: A.3.4 | C86: Fornitura e posa in opera di isolamento interno acustico e/o termico per pareti in cartongesso con lana di vetro/lana di roccia con spessore da valutare. | D86: mq | E86: 0 | F86: 15 | G86: =F86*E86 -> 0 | K86: =F86*$J$26 -> 9.75 | L86: =E86*K86 -> 0 | N86: =G86*0.05 -> 0 | O86: =G86-L86-N86 -> 0 | P86: =O86/G86 -> #DIV/0!
A87: EDILE | B87: A.3.5 | C87: Fornitura e posa in opera di controtelaio in legno per porte interne standard (60-90cm), compresa la quadratura del vano e successiva intonacatura;escluso l'eventuale architrave sottile prefabbricato in calcestruzzo areato autoclavato armato per la realizzazione di aperture su murature interne in blocchi di spessore 8 e 10 cm. SECONDO PROGETTO | D87: cad | E87: 2 | F87: 100 | G87: =F87*E87 -> 200 | K87: =F87*$J$26 -> 65 | L87: =E87*K87 -> 130 | N87: =G87*0.05 -> 10 | O87: =G87-L87-N87 -> 60 | P87: =O87/G87 -> 0.3
A88: EDILE | B88: A.3.6 | C88: Modifica dimensioni porte esistenti, compresa l'eventuale Fornitura e posa in opera di architrave sottile prefabbricato in calcestruzzo aerato autoclavato armato per rendere le porte a misura standard. | D88: cad | E88: 4 | F88: 120 | G88: =F88*E88 -> 480 | H88: Questa voce deve essere presente nel caso di realizzazione di porte su nuova muratura e/o di aperture o spostamenti di porte su murature esistenti. | K88: =F88*$J$26 -> 78 | L88: =E88*K88 -> 312 | N88: =G88*0.05 -> 24 | O88: =G88-L88-N88 -> 144 | P88: =O88/G88 -> 0.3
A89: EDILE | B89: A.3.7 | C89: Fornitura e posa in opera di controtelaio metallico per porte scorrevoli interne al muro, misure standard (60-90cm/spess.10 cm),compresa la quadratura del vano e successiva intonacatura; escluso l'eventuale architrave sottile prefabbricato in calcestruzzo areato autoclavato armato con spessori da 8 a 10 cm. | D89: cad | E89: 1 | F89: 450 | G89: =F89*E89 -> 450 | K89: =F89*$J$26 -> 292.5 | L89: =E89*K89 -> 292.5 | N89: =G89*0.05 -> 22.5 | O89: =G89-L89-N89 -> 135 | P89: =O89/G89 -> 0.3
A90: EDILE | B90: A.3.8 | C90: Realizzazione di quadratura di vano su tramezzi interni per la realizzazione di varchi o l'installazione, compresa la fornitura e posa di angolari metallici e successiva intonacatura. INGRESSO SALA, CUCINA E CAMERA | D90: cad | E90: 3 | F90: 250 | G90: =F90*E90 -> 750 | H90: Questa voce deve essere presente nel caso di apertura di un varco in un muro portante e consiste nella realizzazione di un telaio metallico intorno alla nuova apertura. | K90: =F90*$J$26 -> 162.5 | L90: =E90*K90 -> 487.5 | N90: =G90*0.05 -> 37.5 | O90: =G90-L90-N90 -> 225 | P90: =O90/G90 -> 0.3
B91: A.3 | C91: TOTALE OPERE MURARIE | G91: =SUM(G83:G90) -> 4555 | L91: =SUM(L83:L90) -> 2960.75 | N91: =SUM(N83:N90) -> 227.75 | O91: =SUM(O83:O90) -> 1366.5 | P91: =O91/G91 -> 0.3
B93: A.4 | C93: INTONACI
A94: EDILE | B94: A.4.1 | C94: Intonaco civile realizzato mediante messa a piombo e a squadro di pareti con l'ausilio di fasce guida. NUOVI MURI | D94: mq | E94: 50 | F94: 30 | G94: =F94*E94 -> 1500 | H94: Questa voce dovrà essere computata per i due lati della muratura. Si precisa che nel caso di utilizzo di blocchi Siporex, una volta terminata la parete, è necessario effettuare una rasatura sul muro realizzato con uno strato sottile di: intonaco a base di calce o cemento, oppure utilizzando la stessa colla per blocchi espansi. | K94: =F94*$J$26 -> 19.5 | L94: =E94*K94 -> 975 | N94: =G94*0.05 -> 75 | O94: =G94-L94-N94 -> 450 | P94: =O94/G94 -> 0.3
A95: EDILE | B95: A.4.2 | C95: Ripresa dell'intonaco sulle pareti dove è stato rimosso il rivestimento in ceramica e sulle tracce dei tramezzi demoliti e carta da parati | D95: mq | E95: 85 | F95: 25 | G95: =F95*E95 -> 2125 | H95: Questa voce deve essere presente ogni qualvolta si rimuove un rivestimento e si realizza la finitura a intonaco (da calcolare almeno per il 100% della rimozione rivestimento) e per riprese d'intonaco sulle tracce dei tramezzi demoliti. | K95: =F95*$J$26 -> 16.25 | L95: =E95*K95 -> 1381.25 | N95: =G95*0.05 -> 106.25 | O95: =G95-L95-N95 -> 637.5 | P95: =O95/G95 -> 0.3
B96: A.4 | C96: TOTALE INTONACI | G96: =SUM(G94:G95) -> 3625 | L96: =SUM(L93:L95) -> 2356.25 | N96: =SUM(N94:N95) -> 181.25 | O96: =SUM(O94:O95) -> 1087.5 | P96: =O96/G96 -> 0.3
B98: A.5 | C98: CONTROSOFFITTI e SOPPALCHI
A99: EDILE | B99: A.5.1 | C99: Controsoffitto realizzato con lastre di cartongesso da 12,5 mm, fissate mediante viti autoperforanti ad una struttura costituita da profilati in lamiera di acciaio zincato, comprese la stessa struttura e la stuccatura dei giunti, le opere provvisionali, i ponteggi e quanto altro occorre per dare l’opera finita, esclusa la rasatura. | D99: mq | E99: 0 | F99: 60 | G99: =F99*E99 -> 0 | K99: =F99*$J$26 -> 39 | L99: =E99*K99 -> 0 | N99: =G99*0.05 -> 0 | O99: =G99-L99-N99 -> 0 | P99: =O99/G99 -> #DIV/0!
A100: EDILE | B100: A.5.2 | C100: Isolamento in lana di vetro per controsoffitti, spessore fino a 2cm e di densità pari a 85 kg/mc | D100: mq | E100: 0 | F100: 20 | G100: =F100*E100 -> 0 | K100: =F100*$J$26 -> 13 | L100: =E100*K100 -> 0 | N100: =G100*0.05 -> 0 | O100: =G100-L100-N100 -> 0 | P100: =O100/G100 -> #DIV/0!
A101: EDILE | B101: A.5.3 | C101: Relizzazione di velette in cartongesso da 12,5 mm per controsoffitti, per uno spessore massimo di 10 cm e larghezza massima 30cm per innesto di luce indiretta. | D101: ml | E101: 0 | F101: 50 | G101: =F101*E101 -> 0 | K101: =F101*$J$26 -> 32.5 | L101: =E101*K101 -> 0 | N101: =G101*0.05 -> 0 | O101: =G101-L101-N101 -> 0 | P101: =O101/G101 -> #DIV/0!
A102: EDILE | B102: A.5.4 | C102: Realizzazione di soppalco non abitabile, con struttura metallica e pannelli in cartongesso. Incluse aperture con controtelai in legno ed eslusi pannelli di chiusura. | D102: mq | E102: 0 | F102: 280 | G102: =F102*E102 -> 0 | K102: =F102*$J$26 -> 182 | L102: =E102*K102 -> 0 | N102: =G102*0.05 -> 0 | O102: =G102-L102-N102 -> 0 | P102: =O102/G102 -> #DIV/0!
B103: A.5 | C103: TOTALE CONTROSOFFITTI E SOPPALCHI | G103: =SUM(G99:G102) -> 0 | L103: =SUM(L99:L102) -> 0 | M103: =#REF!*0.4 -> #REF! | N103: =SUM(N99:N102) -> 0 | O103: =SUM(O99:O102) -> 0 | P103: =O103/G103 -> #DIV/0!
B105: A.6 | C105: PAVIMENTI E RIVESTIMENTI
A106: EDILE | B106: A.6.1 | C106: Posa in opera della pavimentazione con disegno a correre, compresa la stuccatura finale (restano escluse colle e stucchi, in quanto andranno scelte e stabilite in funzione del tipo di pavimentazione da posare). TERRAZZA - FORMATO 60X60 | D106: mq | E106: 70 | F106: 30 | G106: =F106*E106 -> 2100 | K106: =F106*$J$26 -> 19.5 | L106: =E106*K106 -> 1365 | N106: =G106*0.05 -> 105 | O106: =G106-L106-N106 -> 630 | P106: =O106/G106 -> 0.3
A107: EDILE | B107: A.6.2 | C107: Posa in opera della pavimentazione con disegno a correre, compresa la stuccatura finale (restano escluse colle e stucchi, in quanto andranno scelte e stabilite in funzione del tipo di pavimentazione da posare). INTERNO CASA - EFFETTO LEGNO 20X120 | D107: mq | E107: 125 | F107: 30 | G107: =F107*E107 -> 3750 | I107: SOLO P.O. | K107: =F107*$J$26 -> 19.5 | L107: =E107*K107 -> 2437.5 | N107: =G107*0.05 -> 187.5 | O107: =G107-L107-N107 -> 1125 | P107: =O107/G107 -> 0.3
A108: EDILE | B108: A.6.3 | C108: Posa in opera dei rivestimenti e stuccatura finale (restano escluse colle e stucchi, in quanto andranno scelte e stabilite in funzione del tipo di pavimentazione da posare). Sono compresi i formati che vanno da 20 a 60 cm coe misure minime e massime ed eventuali cornici di finitura | D108: mq | E108: 0 | F108: 30 | G108: =F108*E108 -> 0 | K108: =F108*$J$26 -> 19.5 | L108: =E108*K108 -> 0 | N108: =G108*0.05 -> 0 | O108: =G108-L108-N108 -> 0 | P108: =O108/G108 -> #DIV/0!
A109: EDILE | B109: A.6.4 | C109: Posa in opera dei rivestimenti e stuccatura finale (restano escluse colle e stucchi, in quanto andranno scelte e stabilite in funzione del tipo di pavimentazione da posare). RIVESTIMENTI BAGNO GRANDE - FORMATO 120X120 | D109: ac | E109: 1 | F109: 2200 | G109: =F109*E109 -> 2200 | I109: SOLO P.O. | K109: =F109*$J$26 -> 1430 | L109: =E109*K109 -> 1430 | N109: =G109*0.05 -> 110 | O109: =G109-L109-N109 -> 660 | P109: =O109/G109 -> 0.3
A110: EDILE | B110: A.6.5 | C110: Posa in opera dei rivestimenti e stuccatura finale (restano escluse colle e stucchi, in quanto andranno scelte e stabilite in funzione del tipo di pavimentazione da posare). RIVESTIMENTI BAGNO CAMERA - FORMATO 60X120 | D110: ac | E110: 1 | F110: 1000 | G110: =F110*E110 -> 1000 | I110: SOLO P.O. | K110: =F110*$J$26 -> 650 | L110: =E110*K110 -> 650 | N110: =G110*0.05 -> 50 | O110: =G110-L110-N110 -> 300 | P110: =O110/G110 -> 0.3
A111: EDILE | B111: A.6.6 | C111: Posa in opera di mosaico di qualsiasi genere, comprese colle e stucchi. | D111: mq | E111: 0 | F111: 60 | G111: =F111*E111 -> 0 | I111: SOLO P.O. | K111: =F111*$J$26 -> 39 | L111: =E111*K111 -> 0 | N111: =G111*0.05 -> 0 | O111: =G111-L111-N111 -> 0 | P111: =O111/G111 -> #DIV/0!
A112: EDILE | B112: A.6.7 | C112: Posa in opera di battiscopa in legno mediante l'ausilio di chiodini senza testa e/o silicone con taglio a 45° per gli angoli, esclusa fornitura, di qualsiasi genere, escluse colle e stucchi. | D112: ml | E112: 90 | F112: 10 | G112: =F112*E112 -> 900 | I112: SOLO P.O. | K112: =F112*$J$26 -> 6.5 | L112: =E112*K112 -> 585 | N112: =G112*0.05 -> 45 | O112: =G112-L112-N112 -> 270 | P112: =O112/G112 -> 0.3
A113: EDILE | B113: A.6.8 | C113: Posa in opera di battiscopa in ceramica mediante l'ausilio di colla, esclusa fornitura, di qualsiasi genere, escluse colle e stucchi. | D113: ml | E113: 0 | F113: 10 | G113: =F113*E113 -> 0 | I113: SOLO P.O. | K113: =F113*$J$26 -> 6.5 | L113: =E113*K113 -> 0 | N113: =G113*0.05 -> 0 | O113: =G113-L113-N113 -> 0 | P113: =O113/G113 -> #DIV/0!
A114: EDILE | B114: A.6.9 | C114: Arrotatura, levigatura e lucidatura di pavimenti in marmo, con mezzo meccanico, compreso ogni onere e magistero per dare il lavoro eseguito a regola d'arte. | D114: mq | E114: 0 | F114: 25 | G114: =F114*E114 -> 0 | K114: =F114*$J$26 -> 16.25 | L114: =E114*K114 -> 0 | N114: =G114*0.05 -> 0 | O114: =G114-L114-N114 -> 0 | P114: =O114/G114 -> #DIV/0!
A115: EDILE | B115: A.6.10 | C115: Levigatura e Lucidatura di pavimenti in parquet, con mezzo meccanico, compreso ogni onere e magistero per dare il lavoro eseguito a regola d'arte. | D115: mq | E115: 0 | F115: 25 | G115: =F115*E115 -> 0 | K115: =F115*$J$26 -> 16.25 | L115: =E115*K115 -> 0 | N115: =G115*0.05 -> 0 | O115: =G115-L115-N115 -> 0 | P115: =O115/G115 -> #DIV/0!
A116: EDILE | B116: A.6.11 | C116: Taglio porta blindata per renderla adatta alla posa nel nuovo pavimento | D116: ac | E116: 0 | F116: 250 | G116: =F116*E116 -> 0 | K116: =F116*$J$26 -> 162.5 | L116: =E116*K116 -> 0 | N116: =G116*0.05 -> 0 | O116: =G116-L116-N116 -> 0 | P116: =O116/G116 -> #DIV/0!
B117: A.6 | C117: TOTALE PAVIMENTI E RIVESTIMENTI | G117: =SUM(G106:G116) -> 9950 | L117: =SUM(L106:L116) -> 6467.5 | N117: =SUM(N106:N116) -> 497.5 | O117: =SUM(O106:O116) -> 2985 | P117: =O117/G117 -> 0.3
B119: A.7 | C119: IMPERMEABILIZZAZIONI
...

Sheet B-FINITURE
E3: ='Analisi preliminareTOTALI'!F3 -> Data : 29/05/2025
E4: Validità Preventivo: 15gg
A6: Dati Cliente
A8: ='Analisi preliminareTOTALI'!A8 -> Cliente caso 04
A9: ='Analisi preliminareTOTALI'!A9 -> Indirizzo
A10: ='Analisi preliminareTOTALI'!A10 -> Reggio Emilia (RE)
A11: ='Analisi preliminareTOTALI'!A11 -> 0
A12: ='Analisi preliminareTOTALI'!A12 -> 0
A13: ='Analisi preliminareTOTALI'!A13 -> 0
A16: DESCRIZIONE | B16: UM: | C16: Qta: | D16: Prezzo Unità | E16: Totale
A18: MATERIALI DI FINITURA
A19: PAVIMENTI E RIVESTIMENTI GRES
A20: Gres porcellanato colorato in massa in piastrelle rettificate, ottenute per pressatura, per pavimentazioni ad intenso calpestio, rispondenti alla norma UNI EN 14411, classe assorbimento acqua BIa UGL: effetto cemento, con superficie antiscivolo (R10 A):30 × 60 cm, naturale o bocciardato, spessore 10mm | B20: mq | C20: 0 | D20: 28.32 | E20: =D20*C20 -> 0
A21: Gres porcellanato colorato in massa in piastrelle rettificate, ottenute per pressatura, per pavimentazioni ad intenso calpestio, rispondenti alla norma UNI EN 14411, classe assorbimento acqua BIa UGL: effetto cemento, con superficie antiscivolo (R10 A): 60 × 60 cm, spessore 15 mm | B21: mq | C21: 0 | D21: 28.32 | E21: =D21*C21 -> 0
A22: Gres porcellanato colorato in massa in piastrelle rettificate, ottenute per pressatura, per pavimentazioni ad intenso calpestio, rispondenti alla norma UNI EN 14411, classe assorbimento acqua BIa UGL: effetto cemento, con superficie antiscivolo (R10 A): 60 × 120 cm, naturale, spessore 10 mm | B22: mq | C22: 0 | D22: 32.32 | E22: =D22*C22 -> 0
A23: Gres porcellanato smaltato in piastrelle, resistente agli sbalzi termici, al gelo e agli acidi, per pavimentazioni ad uso residenziale o terziario leggero, a norma UNI EN 14411 gruppo BIa GL: effetto pietra naturale, rettificato, antiscivolo (R9): 30 × 30 cm, disegno mosaico | B23: mq | C23: 0 | D23: 125 | E23: =D23*C23 -> 0
A24: Gres porcellanato smaltato in piastrelle, resistente agli sbalzi termici, al gelo e agli acidi, per pavimentazioni ad uso residenziale o terziario leggero, a norma UNI EN 14411 gruppo BIa GL:effetto marmo, antiscivolo (R9), spessore 9 mm:30 × 60 cm | B24: mq | C24: 0 | D24: 36.63 | E24: =D24*C24 -> 0
A25: Fornitura di pavimentazione/rivestimento in gres porcelanato TIPO: Padana marmosmart pietrasanta smart honed 60 x 60 1° sc. (mq. 1,44x) | B25: mq | C25: 0 | D25: 23.37 | E25: =D25*C25 -> 0
A26: Gres porcellanato colorato in massa in piastrelle rettificate, ottenute per pressatura, per pavimentazioni ad intenso calpestio, rispondenti alla norma UNI EN 14411, classe assorbimento acqua BIa UGL:effetto cemento, con superficie antiscivolo (R10 A):dimensioni 60 × 60 cm, spessore 15 mm | B26: mq | C26: 0 | D26: 28.32 | E26: =D26*C26 -> 0
A27: Gres porcellanato smaltato in piastrelle, resistente agli sbalzi termici, al gelo e agli acidi, per pavimentazioni ad uso residenziale o terziario leggero, a norma UNI EN 14411 gruppo BIa GL:effetto marmo, antiscivolo (R9), spessore 9 mm:60 × 120 cm | B27: mq | C27: 0 | D27: 38.78 | E27: =D27*C27 -> 0
A28: Gres porcellanato colorato in massa in piastrelle rettificate, ottenute per pressatura, per pavimentazioni ad intenso calpestio, rispondenti alla norma UNI EN 14411, classe assorbimento acqua BIa UGL:effetto cemento, con superficie antiscivolo (R10 A):60 × 120 cm, naturale, spessore 10 mm | B28: mq | C28: 0 | D28: 43.4 | E28: =D28*C28 -> 0
A29: Gres porcellanato smaltato in piastrelle, resistente agli sbalzi termici, al gelo e agli acidi, per pavimentazioni ad uso residenziale o terziario leggero, a norma UNI EN 14411 gruppo BIa GL: effetto pietra naturale, rettificato, antiscivolo (R9): 30 × 60 cm, spessore 10 mm | B29: mq | C29: 0 | D29: 28.32 | E29: =D29*C29 -> 0
A30: Gres porcellanato smaltato in piastrelle, resistente agli sbalzi termici, al gelo e agli acidi, per pavimentazioni ad uso residenziale o terziario leggero, a norma UNI EN 14411 gruppo BIa GL: effetto pietra naturale, rettificato, antiscivolo (R9): 30 × 60 cm, spessore 10 mm | B30: mq | C30: 0 | D30: 28.32 | E30: =D30*C30 -> 0
A31: Gres porcellanato smaltato in piastrelle, resistente agli sbalzi termici, al gelo e agli acidi, per pavimentazioni ad uso residenziale o terziario leggero, a norma UNI EN 14411 gruppo BIa GL: effetto pietra naturale, rettificato, antiscivolo (R9): 60 × 120 cm, spessore 10,5 mm | B31: mq | C31: 0 | D31: 46.9 | E31: =D31*C31 -> 0
... A41: Ceramica monocottura di pasta bianca in lastre ottenute per pressatura, rettificate, per rivestimenti ad uso residenziale, grado di assorbimento acqua gruppo BIII L a norma UNI EN 14411, delle dimensioni di 60 × 180 cm:effetto cemento, strutturato, spessore 9 mm | B41: mq | C41: 0 | D41: 76.3 | E41: =D41*C41 -> 0
A42: PAVIMENTI
A43: Gres porcellanato colorato in massa, ottenuto per pressatura, in lastre di bassissimo spessore rinforzate sul lato inferiore con rete in fibra di vetro, per pavimentazioni ad intenso calpestio, rispondenti alla norma UNI EN 14411, classe reazione al fuoco A2 - s1, classe assorbimento acqua Bia-UGL, nei seguenti formati: effetto legno, spessore 5 mm:20 × 120 cm | B43: mq | C43: 0 | D43: 79.1 | E43: =D43*C43 -> 0
A44: Vinilico multistrato LVT in listoni delle dimensioni di 17 ÷ 20 × 100 ÷ 124 cm o piastre delle dimensioni di 36 × 69 cm con profili laterali ad incastro per posa senza collante, con uno strato d'usura in pvc puro trasparente che protegge uno strato a motivi stampatitrattato con fotoreticolazione UV e laser, resistenza all'abrasione secondo norma EN 660-2 inferiore a 2 mm3 (gruppo T), classe di resistenza allo scivolamento R10 secondo EN 13893 e conforme al test BCRA, classe di reazione al fuoco Bfl-s1 secondo norma EN ISO 13501, isolamento acustico non inferiore a 4 dB secondo EN ISO 717-2, antibatterico secondo ISO 22196, con certificazione EPD e Floorscore/Leed - strato di usura di spessore 0,30 mm, spessore totale 4,50 mm, peso non superiore a 4,10 kg/m2 | B44: mq | C44: 0 | D44: 35.7 | E44: =D44*C44 -> 0
A45: Pavimento in laminato antistatico (< 2 kV - UNI EN 1815 ed UNI EN 14041), con supporto di base in fibra di legno ad elevata densità (HDF) con superficie ad effetto legno, resistenza all'abrasione superficiale in classe AC4 (UNI EN 13329), rigonfiamento del bordo ≤ 18% (valore medio 11% UNI EN 13329), resistenza all'impatto in classe IC2 (UNI EN 13329), con incastro sui 4 lati tipo autocentrante per la posa del tipo flottante mediante incollaggio tra gli elementi, in doghe di spessore 9 mm, lunghezza 2.052 mm e larghezza 200 mm | B45: mq | C45: 0 | D45: 31.88 | E45: =D45*C45 -> 0
A46: Unilin sottofondo in schiuma senza barriera vapore | B46: mq | C46: 0 | D46: 1.76 | E46: =D46*C46 -> 0
A47: Tesserine di vetro per pavimenti a tinta unita delle dimensioni 2 × 2 cm, spessore 4 cm, premontate su fogli di carta dimensioni 30 × 30 cm:colori medi | B47: mq | C47: 0 | D47: 63.2 | E47: =D47*C47 -> 0
A48: Moquette in quadrotte autoposanti idonee alla posa senza collante, ad alta flessibilità, antistatiche, ignifughe di classe 1, dimensioni 50 × 50 cm: con supporto in composto termoplastico rinforzato con due strati di fibre di vetro e pretrattato con antibatterico:100% nylon, superficie velluto disegnato, spessore 9,5 mm | B48: mq | C48: 0 | D48: 98.8 | E48: =D48*C48 -> 0
A49: PAVIMENTI PARQUET
A50: Parquet prefinito in listoni composti da uno strato superiore in legno nobile di spessore 5 mm e supporto in multistrato di betulla con profili maschiati:con superficie prelevigata, da finire in opera, spessore totale 14 mm, lunghezza 1.200 ÷ 2.000 mm, larghezza 140 mm:rovere | B50: mq | C50: 0 | D50: 106.25 | E50: =D50*C50 -> 0
A51: Parquet prefinito in listoni composti da uno strato superiore in legno nobile di spessore 5 mm e supporto in multistrato di betulla con profili maschiati:con superficie prelevigata, da finire in opera, spessore totale 10mm, lunghezza 1.200 ÷ 2.000 mm, larghezza 140 mm:rovere | B51: mq | C51: 0 | D51: 106.25 | E51: =D51*C51 -> 0
A52: Parquet prefinito in listoni composti da uno strato superiore in legno nobile di spessore 5 mm e supporto in multistrato di betulla con profili maschiati:con superficie prelevigata, da finire in opera, spessore totale 14 mm, lunghezza 1.200 ÷ 2.000 mm, larghezza 140 mm: teak | B52: mq | C52: 0 | D52: 165.78 | E52: =D52*C52 -> 0
A53: Parquet prefinito in listoni composti da uno strato superiore in legno nobile di spessore 5 mm e supporto in multistrato di betulla con profili maschiati:con superficie prelevigata, da finire in opera, spessore totale 14 mm, lunghezza 1.200 ÷ 2.000 mm, larghezza 140 mm: iroko | B53: mq | C53: 0 | D53: 108.5 | E53: =D53*C53 -> 0
A54: Parquet prefinito in listoni composti da uno strato superiore in legno nobile di spessore 5 mm e supporto in multistrato di betulla con profili maschiati:con superficie prelevigata, da finire in opera, spessore totale 14 mm, lunghezza 1.200 ÷ 2.000 mm, larghezza 140 mm: rovere | B54: mq | C54: 0 | D54: 106.25 | E54: =D54*C54 -> 0
A55: Parquet prefinito in listoni composti da uno strato superiore in legno nobile di spessore 5 mm e supporto in multistrato di betulla con profili maschiati:con superficie prelevigata, da finire in opera, spessore totale 14 mm, lunghezza 1.200 ÷ 2.000 mm, larghezza 140 mm: wengè | B55: mq | C55: 0 | D55: 166.59 | E55: =D55*C55 -> 0
A56: Parquet prefinito in listoni composti da uno strato superiore in legno nobile di spessore 5 mm e supporto in multistrato di betulla con profili maschiati:con superficie prelevigata, da finire in opera, spessore totale 14 mm, lunghezza 1.200 ÷ 2.000 mm, larghezza 140 mm: wengè | B56: mq | C56: 0 | D56: 113.04 | E56: =D56*C56 -> 0
A57: BATTISCOPA
A58: Zoccolino di gres porcellanato colorato in massa, superficie naturale o bocciardata:effetto cemento, 10 × 30 cm, spessore 8,5 mm con sguscia | B58: ml | C58: 0 | D58: 12.95 | E58: =D58*C58 -> 0
A59: Zoccolino in legno 75 × 10 mm: essenza | B59: ml | C59: 0 | D59: 22.5 | E59: =D59*C59 -> 0
A60: Zoccolino in legno 75 × 10 mm: multistrato bianco | B60: ml | C60: 0 | D60: 9.52 | E60: =D60*C60 -> 0
A61: Zoccolino in legno 40 × 10 mm: multistrato bianco | B61: ml | C61: 0 | D61: 9.52 | E61: =D61*C61 -> 0
A62: Zoccolino in legno 40 × 10 mm: essenza | B62: ml | C62: 0 | D62: 9.52 | E62: =D62*C62 -> 0
A63: MATERIALI DI POSA
A64: Colle, stucchi distanziatori e cunei per la posa | B64: mq | C64: 0 | D64: 3.1 | E64: =D64*C64 -> 0
A65: RUBINETTERIE
A66: Miscelatore monocomando cromato per lavabo con scarico automatico: normale | B66: cad | C66: 0 | D66: 113.14 | E66: =D66*C66 -> 0
A67: Miscelatore monocomando cromato per bidet, erogazione a doccetta orientabile, completo di scarico, senza nipples e rosoni | B67: cad | C67: 0 | D67: 110.4 | E67: =D67*C67 -> 0
A68: Miscelatore cromato monocomando da incasso per doccia/vasca: con corpo incassato, maniglia, cappuccio, rosone, doccia a sistema anticalcare, flessibile da 1500 mm e appendidoccia orientabile. | B68: cad | C68: 0 | D68: 172 | E68: =D68*C68 -> 0
A69: Piatto doccia in acrilico colore bianco, scarico centrale, per installazione sopra pavimento, inclusa piletta sifonata con foro ∅ 90 mm: rettangolare: 120 × 80 × 4 cm o 100 × 80 × 4 cm | B69: cad | C69: 0 | D69: 390 | E69: =D69*C69 -> 0
A70: Vasca in acrilico colore bianco, scarico centrale, per installazione ad incasso, inclusa piletta sifonata con foro ∅ 90 mm: rettangolare: 170 × 70 | B70: cad | C70: 0 | D70: 315 | E70: =D70*C70 -> 0
A71: Cabina per piatto doccia composta da porta con profili in alluminio verniciato a caldo con resine epossidiche, altezza 1850 mm, lastre trasparenti con guarnizioni in gomma trattate con antimuffa, chiusura anta apribile mediante magnete:una porta a soffietto con apertura verso l'interno, con vetro stampato spessore 3 mm: estensibilità 93 ÷ 101 cm | B71: cad | C71: 0 | D71: 544 | E71: =D71*C71 -> 0
A72: Bidet in porcellana dura (vetrochina): monoforo con erogazione dalla rubinetteria, 36 × 54 × 39 cm | B72: cad | C72: 0 | D72: 253 | E72: =D72*C72 -> 0
A73: Vaso igienico in porcellana vetrificata (vetrochina), esclusi accessori di fissaggio: scarico a pavimento | B73: cad | C73: 0 | D73: 310 | E73: =D73*C73 -> 0
A74: Cassetta d'incasso da 9 litri, per posa in muratura, con regolazione del flusso e doppio tipo di risciacquo, allacciamento alla rete idrica sul lato superiore da 1/2", con rubinetto d'arresto, fissaggi per la cassetta e rete di rivestimento per l'intonaco, con tubo di risciacquamento in polietilene e coppelle in polistirolo espanso: per WC a pavimento | B74: cad | C74: 0 | D74: 230.18 | E74: =D74*C74 -> 0
A75: Vaso igienico in porcellana vetrificata (vetrochina), esclusi accessori di fissaggio: sospeso con scarico a parete | B75: cad | C75: 0 | D75: 290.26 | E75: =D75*C75 -> 0
A76: Bidet in porcellana dura (vetrochina): sospeso, monoforo con erogazione dalla rubinetteria. 35 × 57 × 32 cm | B76: cad | C76: 0 | D76: 326 | E76: =D76*C76 -> 0
A77: Cassetta d'incasso da 9 litri, per posa in muratura, con regolazione del flusso e doppio tipo di risciacquo, allacciamento alla rete idrica sul lato superiore da 1/2", con rubinetto d'arresto, fissaggi per la cassetta e rete di rivestimento per l'intonaco, con tubo di risciacquamento in polietilene e coppelle in polistirolo espanso: per WC sospeso, con predisposta curva di allacciamento DN 90 | B77: cad | C77: 0 | D77: 451.47 | E77: =D77*C77 -> 0
A78: Placca di copertura per cassette d'incasso: con tasto di comando e interruzione del risciacquo, in materiale plastico opaca | B78: cad | C78: 0 | D78: 53.77 | E78: =D78*C78 -> 0
A79: Radiatore a rastrelliera realizzato con tubolari orizzontali in acciaio preverniciato con polveri epossidiche a finire di colore bianco, attacchi ∅ 1/2", pressione d'esercizio 8 bar, temperatura massima d'esercizio 95 °C, resa termica con Δ Ti di 50 °C secondo UNI EN 442, in opera compresi valvola termostatizzabile, detentore e mensole di fissaggio:altezza 1.190 mm, larghezza 500 mm, resa termica 595 ± 5% W NB: il prezzo è puramente indicativo in quanto andrà opportunamente dimensionato dal termotecnico | B79: cad | C79: 0 | D79: =193.38*0.67 -> 129.5646 | E79: =D79*C79 -> 0
A80: Radiatori in alluminio ad elementi componibili profondità 95 ÷ 100 mm, preverniciati al forno con polveri epossidiche preassemblati mediante nipples in acciaio, emiss. termica con Δ T50 °C secondo norme UNI EN 442, dati in opera completi di valvola d'intercettazione e detentore, valvola sfogo aria, attacchi ∅ 1", compreso il collegamento alle tubazioni di andata e ritorno dell'impianto: interasse 800 mm; altezza 880 mm; emiss. termica 185 ± 5% W ad elemento: a otto elementi NB: il prezzo è puramente indicativo in quanto andrà opportunamente dimensionato dal termotecnico | B80: cad | C80: 0 | D80: =196.5*0.84 -> 165.06 | E80: =D80*C80 -> 0
A81: TOTALE B "MATERIALI DI FINITURA" iva esclusa | E81: =SUM(E20:E80) -> 0
A82: TOTALE B "MATERIALI DI FINITURA" iva 10% INCLUSA | E82: =E81*1.22 -> 0
A84: Si precisa che il presente documento è idoneo solo a titolo informativo e non costituisce ordinativo e i prezzi potrebbero subire variazioni a seconda del partner selezionato e degli adeguamenti dei listini La scelta definitiva di materiali e finiture andrà finalizzata presso gli show room convenzionati con i nostri partners.

Sheet C- SERRAMENTI PORTE  
E3: ='Analisi preliminareTOTALI'!F3 -> Data : 29/05/2025
E4: Validità Preventivo: 15gg
A6: Dati Cliente
A8: ='Analisi preliminareTOTALI'!A8 -> Cliente caso 04
A9: ='Analisi preliminareTOTALI'!A9 -> Indirizzo
A10: ='Analisi preliminareTOTALI'!A10 -> Reggio Emilia (RE)
A11: ='Analisi preliminareTOTALI'!A11 -> 0
A12: ='Analisi preliminareTOTALI'!A12 -> 0
A13: ='Analisi preliminareTOTALI'!A13 -> 0
A15: DESCRIZIONE | B15: UM: | C15: Qta: | D15: Prezzo Unità | E15: Totale
A17: PORTE
A18: Porta interna in legno con anta mobile tamburata e con bordi impiallacciati, completa di telaio maestro in listellare impiallacciato dello spessore di 8/11 mm, coprifili ad incastro in multistrato e tutta la ferramenta necessaria per il fissaggio, movimento e chiusura, delle dimensioni standard di 210 cm × 60-70-80 cm: anta cieca liscia:noce tanganika | B18: cad | C18: 0 | D18: 192.3 | E18: =D18*C18 -> 0
A19: Porta interna in legno con anta mobile tamburata e con bordi impiallacciati, completa di telaio maestro in listellare impiallacciato dello spessore di 8/11 mm, coprifili ad incastro in multistrato e tutta la ferramenta necessaria per il fissaggio, movimento e chiusura, delle dimensioni standard di 210 cm × 60-70-80 cm: anta cieca liscia:laccata bianca | B19: cad | C19: 0 | D19: 271.2 | E19: =D19*C19 -> 0
A20: Montaggio di porte interne a battente misure standard | B20: cad | C20: 0 | D20: 90 | E20: =D20*C20 -> 0
A21: Porta in legno scorrevole interno muro con anta tamburata e bordi impiallacciati, spessore 8/11 mm, coprifili ad incastro in multistrato, serratura a gancio con nottolino e maniglia ad incasso, dimensioni 210 × 60 ÷ 90 cm:cieca liscia, anta singola:noce tanganika | B21: cad | C21: 0 | D21: 380.4 | E21: =D21*C21 -> 0
A22: Porta in legno scorrevole interno muro con anta tamburata e bordi impiallacciati, spessore 8/11 mm, coprifili ad incastro in multistrato, serratura a gancio con nottolino e maniglia ad incasso, dimensioni 210 × 60 ÷ 90 cm:cieca liscia, anta singola:laccata bianca | B22: cad | C22: 0 | D22: 412.2 | E22: =D22*C22 -> 0
A23: Montaggio di porte interne a scomparsa misure standard | B23: cad | C23: 0 | D23: 95 | E23: =D23*C23 -> 0
A24: Porta blindata costituita da telaio in lamiera d'acciaio dello spessore di 20/10 verniciato e predisposto per l'ancoraggio dei bulloni, controtelaio in lamiera dello spessore di 25/10 verniciato con vernice antiruggine, anta in doppia lamiera d'acciaio dello spessore di 12/10 con profili perimetrali d'acciaio dello spessore di 20/10 e profilo rinforzato dal lato della battuta, rivestita in gomma con truciolare di spessore 7 mm circa finitura liscia; completo di occhio magico, guarnizioni su entrambi i lati, serratura principale e di servizio, compasso di sicurezza, isolamento acustico 35 dB, delle seguenti misure:ad un'anta, luce netta 80 ÷ 90 × 210 cm:noce nazionale | B24: cad | C24: 0 | D24: 801.6 | E24: =D24*C24 -> 0
A25: Rimozione vecchio controtelaio e ripristino delle parti ammalorate mediante stuccatura e verciatura delle parti interessate | B25: cad | C25: 0 | D25: 300 | E25: =D25*C25 -> 0
A26: Montaggio di porta blindata mediante montaggio di nuovo controtelaio e assistenza muraria | B26: cad | C26: 0 | D26: 450 | E26: =D26*C26 -> 0
A27: Finestre a 1/2/3 ante con profilo in PVC , telaio SL LA, colore bianco massa, (5 camere con doppia guarnizione), doppio rinforzo, comprensivo di vetro di sicurezza 2.2.1-18GA-22.1BE. Completo di anta a ribalta, microventilazione, ferramenta e maniglia satinata. La voce comprende fornitura, trasporto e montaggio di infisso nuovo su controtelaio vecchio con smontaggio delle vecchie ante e scarico su fronte strada. Compreso il carico da piano strada e trasporto ad impianti di stoccaggio, di recupero o a discarica. NB:il prezzo è da considerarsi puramente indicativo in quanto andrà confermato previo sopralluogo del serramentista eù dopo la scelta della tipologia di serramento adatta alle proprie esigenze. Quadratura minima da considerare: 2mq | B27: mq | C27: 0 | D27: 760 | E27: =D27*C27 -> 0
A28: Porta finestra a 1/2/3 ante con profilo in PVC , telaio SL LA, colore bianco massa, (5 camere con doppia guarnizione), doppio rinforzo, comprensivo di vetro di sicurezza 2.2.1-18GA-22.1BE. Completo di anta a ribalta, microventilazione, ferramenta e maniglia satinata. La voce comprende fornitura, trasporto e montaggio di infisso nuovo su controtelaio vecchio con smontaggio delle vecchie ante e scarico su fronte strada. Compreso il carico da piano strada e trasporto ad impianti di stoccaggio, di recupero o a discarica. NB:il prezzo è da considerarsi puramente indicativo in quanto andrà confermato previo sopralluogo del serramentista eù dopo la scelta della tipologia di serramento adatta alle proprie esigenze Quadratura minima da considerare: 2mq | B28: mq | C28: 0 | D28: 850 | E28: =D28*C28 -> 0
A29: Tapparelle in PVC effetto legno. La voce comprende fornitura, trasporto e montaggio con smontaggio delle vecchie tapparelle e scarico su fronte strada. Compreso il carico da piano strada e trasporto ad impianti di stoccaggio, di recupero o a discarica. NB:il prezzo è da considerarsi puramente indicativo in quanto andrà confermato previo sopralluogo del serramentista e dopo la scelta della tipologia adatta alle proprie esigenze Quadratura minima da considerare: 2mq | B29: mq | C29: 0 | D29: 280 | E29: =D29*C29 -> 0
... A32: Zanzariere a molla orizzontale e/o a catena e/o scorrevole e/o zanzariera a battente. La voce comprende fornitura, trasporto e montaggio NB:il prezzo è da considerarsi puramente indicativo in quanto andrà confermato previo sopralluogo del serramentista e dopo la scelta della tipologia adatta alle proprie esigenze Quadratura minima da considerare: 2mq | B32: mq | C32: 0 | D32: 200 | E32: =D32*C32 -> 0
A33: TOTALE C "PORTE E SERRAMENTI" iva esclusa | E33: =SUM(E18:E32) -> 0
A34: TOTALE C "PORTE E SERRAMENTI iva 10% INCLUSA | E34: =(E33)*1.1 -> 0
A36: Si precisa che il presente documento è idoneo solo a titolo informativo e non costituisce ordinativo e i prezzi potrebbero subire variazioni a seconda del partner selezionato e degli adeguamenti dei listini La scelta definitiva di porte e serramenti andrà finalizzata presso gli show room convenzionati con i nostri partners. Per l'iter da intraprendere vedi allegato "informativa cliente" al contratto di appalto

Sheet D- PRODOTTI
E3: ='Analisi preliminareTOTALI'!F3 -> Data : 29/05/2025
E4: Validità Preventivo: 15gg
A6: Dati Cliente
A8: ='Analisi preliminareTOTALI'!A8 -> Cliente caso 04
A9: ='Analisi preliminareTOTALI'!A9 -> Indirizzo
A10: ='Analisi preliminareTOTALI'!A10 -> Reggio Emilia (RE)
A11: ='Analisi preliminareTOTALI'!A11 -> 0
A12: ='Analisi preliminareTOTALI'!A12 -> 0
A13: ='Analisi preliminareTOTALI'!A13 -> 0
A15: DESCRIZIONE | B15: UM: | C15: Qta: | D15: Prezzo Unità | E15: Totale
A17: PRODOTTI
A18: Fornitura di condizionatore SAMSUNG CEBU monoplit | B18: cad | C18: 0 | D18: 610 | E18: =D18*C18 -> 0
A19: Fornitura di condizionatore SAMSUNG CEBU dualsplit | B19: cad | C19: 0 | D19: 1358 | E19: =D19*C19 -> 0
A20: Fornitura di condizionatore SAMSUNG CEBU trialsplit | B20: cad | C20: 0 | D20: 2025 | E20: =D20*C20 -> 0
A21: Fornitura di condizionatore DAIKIN PREFERA monoplit | B21: cad | C21: 0 | D21: 1276 | E21: =D21*C21 -> 0
A22: Fornitura di condizionatore DAIKIN PREFERA dualsplit | B22: cad | C22: 0 | D22: 2514 | E22: =D22*C22 -> 0
A23: Fornitura di condizionatore DAIKIN PREFERA trialsplit | B23: cad | C23: 0 | D23: 3852 | E23: =D23*C23 -> 0
A24: Fornitura Caldaia MYNUTE RAIN GREEN E 25 | B24: cad | C24: 0 | D24: 1500 | E24: =D24*C24 -> 0
A25: Fornitura scaldabagno TURBO 12L | B25: cad | C25: 0 | D25: 580 | E25: =D25*C25 -> 0
A26: Fornitura di termosifoni tubolari NOVO 1520/500 | B26: cad | C26: 0 | D26: 350 | E26: =D26*C26 -> 0
A27: Fornitura scaldasalviette NOVO | B27: cad | C27: 0 | D27: 198 | E27: =D27*C27 -> 0
A28: TOTALE D "PRODOTTI" iva esclusa | E28: =SUM(E18:E27) -> 0
A29: TOTALE D "PRODOTTI iva 10% INCLUSA | E29: =(E28)*1.1 -> 0
A31: Si precisa che il presente documento è idoneo solo a titolo informativo e non costituisce ordinativo e i prezzi potrebbero subire variazioni a seconda del partner selezionato e degli adeguamenti dei listini La scelta definitiva di materiali e finiture andrà finalizzata presso gli show room convenzionati con i nostri partners.

Sheet listini
A1: Listini
A2: 0.65
A3: 0.6
A4: 0.55
A5: 0.5

Sheet Importi
A1: IMPORTO CAPITOLATO EDILE BHI | G1: ='A-EDILE'!#REF! -> #REF!
A3: IMPORTO EDILE ASSEVERAZIONE | G3: ='A-EDILE'!#REF! -> #REF!
A5: IMPORTO MATERIALI BHI | G5: ='B-FINITURE'!E81 -> 0
A7: IMPORTO MATERIALI ASSEVERAZIONE | G7: ='B-FINITURE'!E81 -> 0
A9: IMPORTO PORTEI BHI | G9: ='C- SERRAMENTI PORTE '!#REF! -> #REF!
A11: IMPORTO PORTE ASSEVERAZIONE | G11: ='C- SERRAMENTI PORTE '!#REF! -> #REF!

Sheet scheda cantiere_EDILE
A1: SCHEDA CANTIERE:
A3: SERVIZIO-EDILE:
A4: CLIENTE: | B4: ='Analisi preliminareTOTALI'!A8 -> Cliente caso 04 | D4: {='Analisi preliminareTOTALI'!A10:B10} -> Reggio Emilia (RE) | E4: 0
A5: CANTIERE: | B5: {='Analisi preliminareTOTALI'!A9:B9} -> Indirizzo | C5: 0 | D5: {='Analisi preliminareTOTALI'!A12:B12} -> 0 | E5: 0
F6: ENTRATE
A7: IMPORTO firmato: | B7: 0 | D7: data fattura | E7: n.
A8: ACCONTO | B8: =(B7/100)*30 -> 0
A9: SAL 1 | B9: =(B7/100)*20 -> 0
A10: SAL2 | B10: =(B7/100)*40 -> 0 | D10: SCONTO IN FATTURA
A11: SALDO | B11: =(B7/100)*10 -> 0 | D11: SCONTO IN FATTURA
A13: EXTRA CAPITOLATO | B13: IMPORTO | D13: data fattura | E13: n.
A14: n.1 | C14: SCONTO IN FATTURA
A15: n.2 | C15: SCONTO IN FATTURA
A16: n.3 | B16: 0
A17: n.4 | B17: 0
A18: ARCHITETTO:
A21: IMPORTO: | B21: =(B7/100)*5 -> 0 | E21: NOTE | F21: USCITE
C22: data fattura | D22: N.
A23: ACCONTO | B23: =(B21/100)*50 -> 0
A24: SALDO | B24: =B21-B23-+((B14/100)*5)+((B15/100)*5)+((B16/100)*5)+((B17/100)*5) -> 0
A26: SUB APPALTO EDILE: | D26: email@esempio.it
D27: 0
A29: IMPORTO: | B29: 325 | E29: NOTE
C30: data fattura | D30: N.
A31: SAL 1 | B31: =(B29/100)*30 -> 97.5
A32: SAL2 | B32: =(B29/100)*30 -> 97.5
A33: SALDO | B33: =(B29/100)*40 -> 130
A34: EXTRA CAPITOLATO | B34: IMPORTO | C34: data fattura | D34: N.
A35: n.1
A36: n.2
A38: SUB APPALTO ELETTRICO :
A41: IMPORTO: | B41: 0 | E41: NOTE
C42: data fattura | D42: N.
A43: SAL 1 | B43: =(B41/100)*30 -> 0
A44: SAL2 | B44: =(B41/100)*30 -> 0
A45: SALDO | B45: =(B41/100)*40 -> 0
A46: EXTRA CAPITOLATO | B46: IMPORTO | C46: data fattura | D46: N.
A47: n.1
A48: n.2
A50: SUB APPALTO IDRAULICO:
A53: IMPORTO: | B53: 0 | E53: NOTE
C54: data fattura | D54: N.
A55: SAL 1 | B55: =(B53/100)*30 -> 0
A56: SAL2 | B56: =(B53/100)*30 -> 0
A57: SALDO | B57: =(B53/100)*40 -> 0
A58: EXTRA CAPITOLATO | B58: IMPORTO | C58: data fattura | D58: N.
A59: n.1
A60: n.2
A64: Legenda | C64: fattura ricevuta o emessa da pagare
C65: fattura pagata o incassata
C66: fattura ok, in pagamento
G67: =G74/B74 -> #DIV/0!
A68: PREVENTIVI | B68: ENTRATA | C68: USCITE | G68: GUADAGNO
C69: arch. | D69: sub edile | E69: sub elettrico | F69: sub idraulico
A70: Preventivo 1 | B70: =B7 -> 0 | C70: =B21 -> 0 | D70: =B29 -> 325 | E70: =B41 -> 0 | F70: =B53 -> 0 | G70: =B70-C70-D70-E70-F70 -> -325
A71: Extra 1 | B71: =B14 -> 0 | C71: =(B71/100)*5 -> 0 | D71: =B35 -> 0 | E71: =B47 -> 0 | F71: =B59 -> 0 | G71: =B71-C71-D71-E71-F71 -> 0
A72: Extra 2 | B72: =B15 -> 0 | C72: =(B72/100)*5 -> 0 | D72: =B36 -> 0 | E72: =B48 -> 0 | F72: =B60 -> 0 | G72: =B72-C72-D72-E72-F72 -> 0
B74: =B70+B71+B72 -> 0 | C74: =C70+C71+C72 -> 0 | D74: =D70+D71+D72 -> 325 | E74: =E70+E71+E72 -> 0 | F74: =F70+F71+F72 -> 0 | G74: =G70+G71+G72 -> -325

Sheet scheda cantiere_FINITURE
A1: SCHEDA CANTIERE:
A3: FINITURE:
A4: CLIENTE: | B4: ='scheda cantiere_EDILE'!B4 -> Cliente caso 04 | D4: ='scheda cantiere_EDILE'!D4 -> Reggio Emilia (RE)
A5: CANTIERE: | B5: ='scheda cantiere_EDILE'!B5 -> Indirizzo | D5: ='scheda cantiere_EDILE'!D5 -> 0
F6: ENTRATE
A7: IMPORTO firmato: | B7: 0 | D7: data fattura | E7: N.
A9: SALDO | B9: =B7/2 -> 0
A10: SCONTO IN FATTURA | B10: =B7/2 -> 0
A12: EXTRA CAPITOLATO | B12: IMPORTO
A13: n.1 | B13: 0
A14: n.2 | B14: 0
A15: n.3 | B15: 0
A16: n.4 | B16: 0
A18: ARCHITETTO:
F21: USCITE
A22: IMPORTO: | B22: =(B7/100)*5 -> 0
C23: data fattura | D23: N.
A24: SALDO
A26: FORNITORE:
A30: IMPORTO: | B30: 0
C31: scadenza riba
B32: 0
B33: 0
B34: 0
A38: Legenda | C38: fattura ricevuta in firma
C39: fattura pagata o incassata
C40: fattura ok, in pagamento
G41: =G48/B48 -> #DIV/0!
A42: PREVENTIVI | B42: ENTRATA | C42: USCITE | G42: GUADAGNO
C43: arch. | D43: fornitore
A44: Preventivo 1 | B44: =B7 -> 0 | C44: =B22 -> 0 | D44: =B30 -> 0 | G44: =B44-C44-D44-E44-F44 -> 0
A45: Extra 1 | B45: =B13 -> 0 | C45: =(B45/100)*5 -> 0 | D45: 0 | G45: =B45-C45-D45-E45-F45 -> 0
A46: Extra 2 | B46: =B14 -> 0 | C46: =(B46/100)*5 -> 0 | D46: 0 | G46: =B46-C46-D46-E46-F46 -> 0
B48: =B44+B45+B46 -> 0 | C48: =C44+C45+C46 -> 0 | D48: =D44+D45+D46 -> 0 | G48: =G44+G45+G46 -> 0
